{"cameraMode":{"drawMode":0,"name":"Shaded","section":"Shading Mode"},"sceneLighting":true,"audioPlay":false,"sceneViewState":{"showFog":true,"showMaterialUpdate":false,"showSkybox":true,"showFlares":true,"showImageEffects":true,"showParticleSystems":true},"in2DMode":false,"pivot":{"x":0.8951684832572937,"y":-0.7791574597358704,"z":3.2988739013671877},"rotation":{"x":0.11806650459766388,"y":-0.26980969309806826,"z":0.03340151160955429,"w":0.9551439881324768},"size":1839.104248046875,"orthographic":false}